acids_dataset/__init__.py
acids_dataset/add_embedding.py
acids_dataset/cli.py
acids_dataset/info.py
acids_dataset/preprocess.py
acids_dataset/update.py
acids_dataset/utils.py
acids_dataset/configs/after.gin
acids_dataset/configs/default.gin
acids_dataset/configs/rave.gin
acids_dataset/datasets/__init__.py
acids_dataset/datasets/combined.py
acids_dataset/datasets/simple.py
acids_dataset/datasets/utils.py
acids_dataset/features/__init__.py
acids_dataset/features/base.py
acids_dataset/features/beat_tracking.py
acids_dataset/features/clustering.py
acids_dataset/features/cqt.py
acids_dataset/features/loudness.py
acids_dataset/features/mel.py
acids_dataset/features/midi.py
acids_dataset/features/module.py
acids_dataset/features/pitch.py
acids_dataset/features/regexp.py
acids_dataset/features/beat_this/__init__.py
acids_dataset/features/beat_this/cli.py
acids_dataset/features/beat_this/inference.py
acids_dataset/features/beat_this/preprocessing.py
acids_dataset/features/beat_this/utils.py
acids_dataset/features/beat_this/model/__init__.py
acids_dataset/features/beat_this/model/beat_tracker.py
acids_dataset/features/beat_this/model/loss.py
acids_dataset/features/beat_this/model/pl_module.py
acids_dataset/features/beat_this/model/postprocessor.py
acids_dataset/features/beat_this/model/roformer.py
acids_dataset/fragments/__init__.py
acids_dataset/fragments/acids.py
acids_dataset/fragments/base.py
acids_dataset/fragments/utils.py
acids_dataset/fragments/compiled/__init__.py
acids_dataset/fragments/compiled/acids_pb2.py
acids_dataset/loaders/__init__.py
acids_dataset/loaders/balanced.py
acids_dataset/parsers/__init__.py
acids_dataset/parsers/raw_parser.py
acids_dataset/parsers/utils.py
acids_dataset/transforms/__init__.py
acids_dataset/transforms/audiomentations.py
acids_dataset/transforms/base.py
acids_dataset/transforms/misc.py
acids_dataset/transforms/pitch.py
acids_dataset/transforms/resample_poly.py
acids_dataset/transforms/utils.py
acids_dataset-0.1.0.dist-info/licenses/LICENSE
acids_dataset-0.1.0.dist-info/METADATA
acids_dataset-0.1.0.dist-info/WHEEL
acids_dataset-0.1.0.dist-info/entry_points.txt
acids_dataset-0.1.0.dist-info/top_level.txt
acids_dataset-0.1.0.dist-info/RECORD
