Metadata-Version: 2.4
Name: acids_dataset
Version: 0.1.0
Summary: a pre-processing & dataloading library for generative audio ML
Author: Antoine Caillon
Author-email: Axel Chemla Romeu Santos <chemla@ircam.fr>, Nils Demerlé <demerle@ircam.fr>
Project-URL: Homepage, https://github.com/acids-ircam/acids-dataset
Project-URL: Issues, https://github.com/acids-ircam/acids-dataset/issues
Classifier: Programming Language :: Python :: 3
Classifier: Operating System :: OS Independent
Requires-Python: >=3.11
License-File: LICENSE
Requires-Dist: pytest
Requires-Dist: grpcio-tools==1.71.0
Requires-Dist: absl-py
Requires-Dist: PyYAML
Requires-Dist: gin-config
Requires-Dist: lmdb
Requires-Dist: tqdm
Requires-Dist: dill
Requires-Dist: numpy==2.1
Requires-Dist: scipy==1.15.2
Requires-Dist: scikit-learn==1.6.1
Requires-Dist: librosa==0.10.2
Requires-Dist: torch
Requires-Dist: torchaudio
Requires-Dist: pytorch_lightning
Requires-Dist: pydub
Requires-Dist: pyroomacoustics
Requires-Dist: pyloudnorm
Requires-Dist: nnaudio
Requires-Dist: mir_eval
Requires-Dist: resampy
Requires-Dist: pretty_midi
Requires-Dist: einops
Requires-Dist: rotary_embedding_torch
Requires-Dist: audiomentations
Dynamic: license-file
